{"cameraMode":{"drawMode":0,"name":"Shaded","section":"Shading Mode"},"sceneLighting":true,"audioPlay":false,"sceneViewState":{"showFog":true,"showMaterialUpdate":false,"showSkybox":true,"showFlares":true,"showImageEffects":true,"showParticleSystems":true},"in2DMode":false,"pivot":{"x":-40.922210693359378,"y":-3.703868865966797,"z":-35.157657623291019},"rotation":{"x":-0.1494799554347992,"y":0.8090806007385254,"z":-0.2333643138408661,"w":-0.5182519555091858},"size":57.109928131103519,"orthographic":false}